mkdocs_intersphinx/__init__.py
mkdocs_intersphinx/inventory.py
mkdocs_intersphinx/parser.py
mkdocs_intersphinx/plugin.py
mkdocs_intersphinx-0.1.1.dist-info/entry_points.txt
mkdocs_intersphinx-0.1.1.dist-info/WHEEL
mkdocs_intersphinx-0.1.1.dist-info/METADATA
mkdocs_intersphinx-0.1.1.dist-info/RECORD
