Metadata-Version: 2.4
Name: mkdocs-intersphinx
Version: 0.1.1
Summary: MkDocs plugin to generate Sphinx-compatible objects.inv for intersphinx cross-referencing
Author: M Bussonnier
Requires-Python: >=3.12
Classifier: Development Status :: 3 - Alpha
Classifier: Intended Audience :: Developers
Classifier: License :: OSI Approved :: MIT License
Classifier: Programming Language :: Python :: 3
Classifier: Topic :: Documentation
Classifier: Topic :: Software Development :: Documentation
Requires-Dist: mkdocs>=1.5.0
Requires-Dist: sphobjinv>=2.3.0
Requires-Dist: pytest>=7.0 ; extra == "dev"
Requires-Dist: pytest-cov>=4.0 ; extra == "dev"
Requires-Dist: mypy>=1.0 ; extra == "dev"
Project-URL: Homepage, https://github.com/carreau/mkdocs_intersphinx
Provides-Extra: dev
